briefcase_debugger.pth
briefcase_debugger/__init__.py
briefcase_debugger/config.py
briefcase_debugger/debugpy.py
briefcase_debugger/pdb.py
briefcase_debugger-0.3.26.dist-info/licenses/LICENSE
briefcase_debugger-0.3.26.dist-info/METADATA
briefcase_debugger-0.3.26.dist-info/WHEEL
briefcase_debugger-0.3.26.dist-info/top_level.txt
briefcase_debugger-0.3.26.dist-info/RECORD
