Metadata-Version: 2.4
Name: briefcase-debugger
Version: 0.3.26
Summary: A Briefcase plugin adding remote debugging support for PDB and Visual Studio Code.
License-Expression: BSD-3-Clause
License-File: LICENSE
Provides-Extra: pdb
Requires-Dist: remote-pdb<3.0.0,>=2.1.0; extra == "pdb"
Provides-Extra: debugpy
Requires-Dist: debugpy<2.0.0,>=1.8.17; extra == "debugpy"
Dynamic: license-file
